cdk_github_oidc/__init__.py
cdk_github_oidc/py.typed
cdk_github_oidc/_jsii/__init__.py
cdk_github_oidc/_jsii/cdk-github-oidc@1.1.0.jsii.tgz
cdk_github_oidc-1.1.0.dist-info/LICENSE
cdk_github_oidc-1.1.0.dist-info/METADATA
cdk_github_oidc-1.1.0.dist-info/WHEEL
cdk_github_oidc-1.1.0.dist-info/top_level.txt
cdk_github_oidc-1.1.0.dist-info/RECORD
