Metadata-Version: 2.1
Name: cdk-github-oidc
Version: 1.1.0
Summary: AWS CDK construct to create OIDC roles for CircleCI jobs
Home-page: https://github.com/blimmer/cdk-github-oidc.git
Author: Ben Limmer<hello@benlimmer.com>
License: Apache-2.0
Project-URL: Source, https://github.com/blimmer/cdk-github-oidc.git
Classifier: Intended Audience :: Developers
Classifier: Operating System :: OS Independent
Classifier: Programming Language :: JavaScript
Classifier: Programming Language :: Python :: 3 :: Only
Classifier: Programming Language :: Python :: 3.9
Classifier: Programming Language :: Python :: 3.10
Classifier: Programming Language :: Python :: 3.11
Classifier: Typing :: Typed
Classifier: Development Status :: 5 - Production/Stable
Classifier: License :: OSI Approved
Requires-Python: ~=3.9
License-File: LICENSE
Requires-Dist: aws-cdk-lib <3.0.0,>=2.73.0
Requires-Dist: constructs <11.0.0,>=10.0.5
Requires-Dist: jsii <2.0.0,>=1.113.0
Requires-Dist: publication >=0.0.3
Requires-Dist: typeguard <4.3.0,>=2.13.3
